{
  "id": "70e1abb2-77b5-4384-a163-3a5330933831",
  "name": "Fuel Price Data Qualiyt Project",
  "description": "Montoring to track the data quality for a fuel price forecasting model",
  "dashboard": {
    "name": "Fuel Price Data Qualiyt Project",
    "panels": [
      {
        "type": "evidently.ui.dashboards.reports.DashboardPanelCounter",
        "id": "98c2d6bd-5c4c-40ed-91d8-3658267a7868",
        "title": "Super 95 fuel price data dashboard",
        "filter": {
          "metadata_values": {},
          "tag_values": [],
          "include_test_suites": false
        },
        "size": 2,
        "agg": "none",
        "value": null,
        "text": null
      },
      {
        "type": "evidently.ui.dashboards.reports.DashboardPanelPlot",
        "id": "cc822d9a-7301-4f26-86f7-7417d799eefb",
        "title": "Inference Count",
        "filter": {
          "metadata_values": {},
          "tag_values": [],
          "include_test_suites": false
        },
        "size": 1,
        "values": [
          {
            "field_path": "current.number_of_rows",
            "metric_id": "DatasetSummaryMetric",
            "metric_fingerprint": null,
            "metric_args": {},
            "legend": "count"
          }
        ],
        "plot_type": "bar"
      },
      {
        "type": "evidently.ui.dashboards.reports.DashboardPanelPlot",
        "id": "d0a92645-efc6-44b1-8aa9-438629087b52",
        "title": "Number of Missing Values",
        "filter": {
          "metadata_values": {},
          "tag_values": [],
          "include_test_suites": false
        },
        "size": 1,
        "values": [
          {
            "field_path": "current.number_of_missing_values",
            "metric_id": "DatasetSummaryMetric",
            "metric_fingerprint": null,
            "metric_args": {},
            "legend": "count"
          }
        ],
        "plot_type": "line"
      }
    ],
    "tabs": [],
    "tab_id_to_panel_ids": {}
  },
  "team_id": null,
  "date_from": null,
  "date_to": null,
  "created_at": "2024-08-11T17:05:40.205418"
}